.gitignore
LICENSE
README.md
RELEASE_NOTES
pyproject.toml
setup.cfg
setup.py
.github/workflows/automatic_versioning.yml
.github/workflows/check_versions.yml
.github/workflows/linting.yml
.github/workflows/pip_install.yml
.github/workflows/scorecards.yml
.github/workflows/test.yml
.github/workflows/test_docs.yml
CI/README.md
CI/run_reframe.sh
CI/run_reframe_wrapper.sh
CI/aws_mc/ci_config.sh
CI/azure_mc/ci_config.sh
CI/hortense_EESSI_ss/ci_config.sh
CI/hortense_local_ss/ci_config.sh
CI/it4i_karolina/ci_config.sh
CI/izum_vega/ci_config.sh
CI/surf_snellius/ci_config.sh
config/aws_citc.py
config/aws_mc.py
config/azure_mc.py
config/bsc_marenostrum5.py
config/github_actions.py
config/it4i_karolina.py
config/izum_vega.py
config/macc_deucalion.py
config/settings_example.py
config/surf_snellius.py
config/vsc_hortense.py
eessi/__init__.py
eessi/testsuite/__init__.py
eessi/testsuite/_version.py
eessi/testsuite/common_config.py
eessi/testsuite/constants.py
eessi/testsuite/eessi_mixin.py
eessi/testsuite/hooks.py
eessi/testsuite/utils.py
eessi/testsuite/tests/__init__.py
eessi/testsuite/tests/apps/MetalWalls.py
eessi/testsuite/tests/apps/QuantumESPRESSO.py
eessi/testsuite/tests/apps/__init__.py
eessi/testsuite/tests/apps/gromacs.py
eessi/testsuite/tests/apps/osu.py
eessi/testsuite/tests/apps/PyTorch/PyTorch_torchvision.py
eessi/testsuite/tests/apps/PyTorch/__init__.py
eessi/testsuite/tests/apps/PyTorch/src/__init__.py
eessi/testsuite/tests/apps/PyTorch/src/get_free_socket.py
eessi/testsuite/tests/apps/PyTorch/src/pytorch_synthetic_benchmark.py
eessi/testsuite/tests/apps/cp2k/README.md
eessi/testsuite/tests/apps/cp2k/__init__.py
eessi/testsuite/tests/apps/cp2k/cp2k.py
eessi/testsuite/tests/apps/cp2k/src/__init__.py
eessi/testsuite/tests/apps/cp2k/src/QS/H2O-128.inp
eessi/testsuite/tests/apps/cp2k/src/QS/H2O-32.inp
eessi/testsuite/tests/apps/cp2k/src/QS/H2O-512.inp
eessi/testsuite/tests/apps/cp2k/src/QS/__init__.py
eessi/testsuite/tests/apps/espresso/__init__.py
eessi_testsuite.egg-info/PKG-INFO
eessi_testsuite.egg-info/SOURCES.txt
eessi_testsuite.egg-info/dependency_links.txt
eessi_testsuite.egg-info/namespace_packages.txt
eessi_testsuite.egg-info/requires.txt
eessi_testsuite.egg-info/top_level.txt
