Metadata-Version: 2.2
Name: eessi-testsuite
Version: 0.9.0
Summary: Test suite for the EESSI software stack
License:                     GNU GENERAL PUBLIC LICENSE
Project-URL: Homepage, https://eessi.io/docs/test-suite
Project-URL: Bug Tracker, https://github.com/EESSI/test-suite/issues
Classifier: Programming Language :: Python
Requires-Python: >=3.6
License-File: LICENSE
Provides-Extra: compilation
Requires-Dist: easybuild; extra == "compilation"
